package/__init__.py
package/create_django_project.py
package/ecommerce_generator.py
package/form_generator.py
package/generate_django_app.py
package/lib.py
package/model_generator.py
package/module.py
package/template_generator.py
package/view_generator.py
mudey_django-2.5.dist-info/METADATA
mudey_django-2.5.dist-info/WHEEL
mudey_django-2.5.dist-info/entry_points.txt
mudey_django-2.5.dist-info/top_level.txt
mudey_django-2.5.dist-info/RECORD
