Metadata-Version: 2.1
Name: mudey-django
Version: 2.5
Summary: CLI Django
Author: Espero-Soft Informatiques
Author-email: contact@espero-soft.com
License: MIT
Classifier: Programming Language :: Python :: 2.7
Classifier: Programming Language :: Python :: 3
Classifier: Programming Language :: Python :: 3.7
Classifier: Programming Language :: Python :: 3.8
Classifier: License :: OSI Approved :: MIT License
Classifier: Operating System :: OS Independent
Requires-Dist: annotated-types >=0.6.0
Requires-Dist: Django >=5.0
Requires-Dist: django >=5.0
Requires-Dist: inflect >=7.0.0
Requires-Dist: questionary >=2.0.1
Requires-Dist: colorama >=0.4.6
Requires-Dist: setuptools >=69.0.0
